grey_harvest.py
grey_harvest-0.1.3.5.dist-info/DESCRIPTION.rst
grey_harvest-0.1.3.5.dist-info/entry_points.txt
grey_harvest-0.1.3.5.dist-info/METADATA
grey_harvest-0.1.3.5.dist-info/metadata.json
grey_harvest-0.1.3.5.dist-info/RECORD
grey_harvest-0.1.3.5.dist-info/top_level.txt
grey_harvest-0.1.3.5.dist-info/WHEEL
