Metadata-Version: 2.0
Name: grey-harvest
Version: 0.1.3.5
Summary: Generate lists of free, reliable http(s) proxies.
Home-page: https://github.com/s0lst1c3/grey_harvest
Author: John "s0lst1c3" Ryan
Author-email: contact@solstice.me
License: MIT
Download-URL: https://github.com/s0lst1c3/grey_harvest/tarball/0.1.2
Platform: UNKNOWN
Classifier: Development Status :: 3 - Alpha
Classifier: Environment :: Console
Classifier: Intended Audience :: Developers
Classifier: Intended Audience :: Science/Research
Classifier: Intended Audience :: System Administrators
Classifier: License :: OSI Approved :: MIT License
Classifier: Natural Language :: English
Classifier: Operating System :: MacOS :: MacOS X
Classifier: Operating System :: POSIX
Classifier: Operating System :: POSIX :: Linux
Classifier: Programming Language :: Python :: 2.7
Classifier: Topic :: Internet :: Proxy Servers
Classifier: Topic :: Internet :: WWW/HTTP
Classifier: Topic :: Security
Classifier: Topic :: Software Development :: Libraries :: Python Modules
Classifier: Topic :: System :: Systems Administration
Classifier: Topic :: Utilities
Requires-Dist: requests
Requires-Dist: pyOpenSSL
Requires-Dist: beautifulsoup4
Requires-Dist: lxml
Requires-Dist: argparse
